executor/__init__.py
executor/app.py
executor/executor.py
executor/httpservice.py
executor/job.py
executor/notifier.py
executor/scheduler.py
yqgscheduler-0.1.2.dist-info/METADATA
yqgscheduler-0.1.2.dist-info/WHEEL
yqgscheduler-0.1.2.dist-info/top_level.txt
yqgscheduler-0.1.2.dist-info/RECORD
