Metadata-Version: 2.1
Name: yqgscheduler
Version: 0.1.2
Summary: 分布式scheduler的executor部分的python实现
Home-page: UNKNOWN
Author: xhgao
Author-email: xhgao@yangqianguan.com
License: UNKNOWN
Platform: UNKNOWN
Requires-Dist: flask
